qtcodeedit.py
qtcodeedit-0.1.0.dist-info/METADATA
qtcodeedit-0.1.0.dist-info/WHEEL
qtcodeedit-0.1.0.dist-info/licenses/LICENSE
qtcodeedit-0.1.0.dist-info/RECORD
