Metadata-Version: 2.3
Name: qtcodeedit
Version: 0.1.0
Summary: A code editing widget for PyQt and PySide
Project-URL: Homepage, https://github.com/kaofelix/qtcodeedit
Project-URL: Issues, https://github.com/kaofelix/qtcodeedit
Author-email: Kao Cardoso Félix <kcfelix@gmail.com>
License-File: LICENSE
Classifier: License :: OSI Approved :: MIT License
Classifier: Operating System :: OS Independent
Classifier: Programming Language :: Python :: 3
Requires-Python: >=3.10
Requires-Dist: pygments>=2.18.0
Requires-Dist: pyside6>=6.2.0
Requires-Dist: qtpy>=2.4.1
